nr_pypackage/__init__.py
nr_pypackage/cli_main.py
nr_pypackage/cli_package.py
nr_pypackage/package_creator.py
nr_pypackage/utils.py
nr_pypackage/blueprints/__init__.py
nr_pypackage/blueprints/blueprint_auth.py
nr_pypackage/blueprints/blueprints.py
nr_pypackage/blueprints/blueprint_database/__init__.py
nr_pypackage/blueprints/blueprint_database/blueprint_database.py
nr_pypackage/blueprints/blueprint_database/ui_columns.py
nr_pypackage/blueprints/blueprint_database/ui_table.py
nr_pypackage/templates/package_blueprints/.gitignore
nr_pypackage/templates/package_blueprints/.travis.yml
nr_pypackage/templates/package_blueprints/LICENSE
nr_pypackage/templates/package_blueprints/MANIFEST.in
nr_pypackage/templates/package_blueprints/Makefile
nr_pypackage/templates/package_blueprints/README.md
nr_pypackage/templates/package_blueprints/activate-env.sh
nr_pypackage/templates/package_blueprints/dev_environment.yml
nr_pypackage/templates/package_blueprints/requirements.txt
nr_pypackage/templates/package_blueprints/setup.cfg
nr_pypackage/templates/package_blueprints/setup.py
nr_pypackage/templates/package_blueprints/PACKAGE_NAME_SAFE/__init__.py
nr_pypackage/templates/package_blueprints/PACKAGE_NAME_SAFE/service/__init__.py
nr_pypackage/templates/package_blueprints/PACKAGE_NAME_SAFE/service/server.py
nr_pypackage/templates/package_blueprints/PACKAGE_NAME_SAFE/service/BP_DATABASE/__init__.py
nr_pypackage/templates/package_blueprints/PACKAGE_NAME_SAFE/service/BP_DATABASE/db_create.py
nr_pypackage/templates/package_blueprints/PACKAGE_NAME_SAFE/service/BP_DATABASE/db_delete.py
nr_pypackage/templates/package_blueprints/PACKAGE_NAME_SAFE/service/BP_DATABASE/db_manager.py
nr_pypackage/templates/package_blueprints/PACKAGE_NAME_SAFE/service/BP_DATABASE/TABLE_NAME/TABLE_NAME_api.py
nr_pypackage/templates/package_blueprints/PACKAGE_NAME_SAFE/service/BP_DATABASE/TABLE_NAME/TABLE_NAME_model.py
nr_pypackage-0.3.0.dist-info/LICENSE
nr_pypackage-0.3.0.dist-info/METADATA
nr_pypackage-0.3.0.dist-info/WHEEL
nr_pypackage-0.3.0.dist-info/entry_points.txt
nr_pypackage-0.3.0.dist-info/top_level.txt
nr_pypackage-0.3.0.dist-info/RECORD
