Metadata-Version: 2.1
Name: nr-pypackage
Version: 0.3.0
Summary: Some description about your project
Home-page: UNKNOWN
Author: Nitish Reddy Koripalli
Author-email: nitish.k.reddy@gmail.com
License: UNKNOWN
Platform: UNKNOWN
Classifier: Programming Language :: Python :: 2
Classifier: Programming Language :: Python :: 2.7
Classifier: Programming Language :: Python :: 3
Classifier: Programming Language :: Python :: 3.4
Classifier: Programming Language :: Python :: 3.5
Classifier: Programming Language :: Python :: 3.6
Requires-Dist: future
Requires-Dist: Jinja2 (>=2.10)
Requires-Dist: click (>=7.0)
Requires-Dist: prompt-toolkit (>=2.0.5)
Requires-Dist: python-box (>=3.2.0)
